topsis/__main__.py
shadowtopsis-1.0.0.dist-info/LICENSE
shadowtopsis-1.0.0.dist-info/METADATA
shadowtopsis-1.0.0.dist-info/WHEEL
shadowtopsis-1.0.0.dist-info/entry_points.txt
shadowtopsis-1.0.0.dist-info/top_level.txt
shadowtopsis-1.0.0.dist-info/RECORD
